ConMedRL/__init__.py
ConMedRL/conmedrl.py
ConMedRL/conmedrl_continuous.py
ConMedRL/data_loader.py
Data/__init__.py
Data/SICdb_discharge/__init__.py
Data/SICdb_discharge/data_preprocess.py
Data/SICdb_extubation/__init__.py
Data/SICdb_extubation/data_preprocess.py
Data/mimic_iv_icu_discharge/__init__.py
Data/mimic_iv_icu_discharge/data_preprocess.py
Data/mimic_iv_icu_extubation/__init__.py
Data/mimic_iv_icu_extubation/data_preprocess.py
conmedrl-1.0.6.dist-info/licenses/LICENSE
conmedrl-1.0.6.dist-info/METADATA
conmedrl-1.0.6.dist-info/WHEEL
conmedrl-1.0.6.dist-info/top_level.txt
conmedrl-1.0.6.dist-info/RECORD
