Metadata-Version: 2.4
Name: ConMedRL
Version: 1.0.6
Summary: An Offline Constrained Reinforcement Learning Toolkit for Medical Decision Making
Home-page: https://github.com/smt970913/ConMED-RL
Author: Maotong Sun, Jingui Xie
Author-email: Maotong Sun <maotong.sun@tum.de>, Jingui Xie <jingui.xie@tum.de>
Maintainer-email: Maotong Sun <maotong.sun@tum.de>, Jingui Xie <jingui.xie@tum.de>
License: MIT License
Project-URL: Homepage, https://github.com/smt970913/ConMED-RL
Project-URL: Documentation, https://github.com/smt970913/ConMED-RL#readme
Project-URL: Repository, https://github.com/smt970913/ConMED-RL
Project-URL: Bug Tracker, https://github.com/smt970913/ConMED-RL/issues
Keywords: reinforcement learning,constrained reinforcement learning,offline reinforcement learning,clinical decision support,healthcare,ICU,critical care,machine learning,artificial intelligence
Classifier: Development Status :: 4 - Beta
Classifier: Intended Audience :: Healthcare Industry
Classifier: Intended Audience :: Science/Research
Classifier: Topic :: Scientific/Engineering :: Artificial Intelligence
Classifier: Topic :: Scientific/Engineering :: Medical Science Apps.
Classifier: License :: OSI Approved :: MIT License
Classifier: Programming Language :: Python :: 3
Classifier: Programming Language :: Python :: 3.8
Classifier: Programming Language :: Python :: 3.9
Classifier: Programming Language :: Python :: 3.10
Classifier: Operating System :: OS Independent
Requires-Python: >=3.8
License-File: LICENSE
Requires-Dist: flask==2.2.2
Requires-Dist: scikit-learn==1.2.1
Requires-Dist: torch>=1.8.0
Requires-Dist: numpy==1.23.5
Requires-Dist: pandas==1.5.3
Requires-Dist: tqdm==4.64.1
Requires-Dist: celery==5.3.6
Requires-Dist: gunicorn==20.1.0
Requires-Dist: pillow==9.4.0
Requires-Dist: requests==2.31.0
Requires-Dist: dask[complete]>=2023.1.0
Requires-Dist: threadpoolctl>=3.1.0
Requires-Dist: joblib>=1.2.0
Requires-Dist: jupyter==1.0.0
Requires-Dist: jupyterlab==4.0.5
Requires-Dist: notebook==7.0.2
Requires-Dist: matplotlib==3.7.1
Requires-Dist: seaborn==0.12.2
Requires-Dist: plotly==5.17.0
Provides-Extra: dev
Requires-Dist: pytest>=6.0; extra == "dev"
Requires-Dist: pytest-cov>=2.0; extra == "dev"
Requires-Dist: black>=21.0; extra == "dev"
Requires-Dist: flake8>=3.8; extra == "dev"
Requires-Dist: jupyter>=1.0; extra == "dev"
Requires-Dist: notebook>=6.0; extra == "dev"
Provides-Extra: models
Requires-Dist: torch>=1.8.0; extra == "models"
Requires-Dist: torchvision>=0.9.0; extra == "models"
Provides-Extra: viz
Requires-Dist: matplotlib>=3.3.0; extra == "viz"
Requires-Dist: seaborn>=0.11.0; extra == "viz"
Requires-Dist: plotly>=5.0.0; extra == "viz"
Dynamic: author
Dynamic: home-page
Dynamic: license-file
Dynamic: requires-python
